{
  "type": "EFFECT_REQUESTED",
  "recordedAt": "2026-02-16T10:34:51.662Z",
  "data": {
    "effectId": "01KHK08TWE5Q0WY89509KGN8PS",
    "invocationKey": "content/publish-queue:S000004:draft-release-notes",
    "invocationHash": "1f87e2572206cfa9e456c27fcf91f7ba3375331adddd5452a9af5dcac491395b",
    "stepId": "S000004",
    "taskId": "draft-release-notes",
    "kind": "agent",
    "label": "Draft release notes",
    "taskDefRef": "tasks/01KHK08TWE5Q0WY89509KGN8PS/task.json"
  },
  "checksum": "930eb49b64d3e4f0fb25642d7e429ec1b5e0b0affc24c1ecacfa3e183fffc635"
}
