{
  "schemaVersion": "2026.01.tasks-v1",
  "effectId": "01KHGHE7Z2PQDBRY6YG44Y549D",
  "taskId": "validate-schema",
  "invocationKey": "content/analytics-roll:S000004:validate-schema",
  "stepId": "S000004",
  "kind": "node",
  "title": "Validate schema",
  "io": {
    "inputJsonPath": "tasks/01KHGHE7Z2PQDBRY6YG44Y549D/input.json",
    "outputJsonPath": "tasks/01KHGHE7Z2PQDBRY6YG44Y549D/result.json"
  },
  "inputs": {
    "records": 5729,
    "batchSize": 259,
    "source": "s3",
    "destination": "postgres"
  }
}
