{
  "type": "EFFECT_REQUESTED",
  "recordedAt": "2026-02-17T01:47:00.596Z",
  "data": {
    "effectId": "01KHMMF13M9NQEYV1W7X2H58EP",
    "invocationKey": "content/publish-queue:S000012:deduplicate-records",
    "invocationHash": "56728c05dc0fe22a2123471a2ea69f0ff8637dda6f5b32ec6af50026adc260ef",
    "stepId": "S000012",
    "taskId": "deduplicate-records",
    "kind": "node",
    "label": "Deduplicate records",
    "taskDefRef": "tasks/01KHMMF13M9NQEYV1W7X2H58EP/task.json"
  },
  "checksum": "08d0d1ff15b9e6667f608f7f1ddca1ee2e52d90443ee5f9f7336944045295b9e"
}
